ml_ude_client/__init__.py
ml_ude_client/client.py
ml_ude_client/memory.py
ml_ude_client-0.1.1.dist-info/METADATA
ml_ude_client-0.1.1.dist-info/WHEEL
ml_ude_client-0.1.1.dist-info/RECORD
